nautilopy/__init__.py
nautilopy/core.py
nautilopy-0.1.0.dist-info/METADATA
nautilopy-0.1.0.dist-info/WHEEL
nautilopy-0.1.0.dist-info/top_level.txt
nautilopy-0.1.0.dist-info/RECORD
