Metadata-Version: 2.4
Name: nautilopy
Version: 0.1.0
Summary: Tools for preprocessing and analysis of underwater acoustic data.
Project-URL: Homepage, https://github.com/20KUTS/nautilopy
Requires-Python: >=3.12
Requires-Dist: bagpy==0.5
Requires-Dist: fastcore==1.7.11
Requires-Dist: ipython==8.28.0
Requires-Dist: ipywidgets==8.1.5
Requires-Dist: jupyterlab>=4.3.3
Requires-Dist: jupyterlab-myst>=2.4.2
Requires-Dist: matplotlib==3.9.2
Requires-Dist: nbdev==2.3.31
Requires-Dist: numpy==2.1.2
Requires-Dist: pandas==2.2.3
Requires-Dist: pillow==11.0.0
Requires-Dist: plotly==5.24.1
Requires-Dist: pytest==8.3.3
Requires-Dist: scikit-image==0.24.0
Requires-Dist: scipy==1.14.1
